scalecodec/__init__.py
scalecodec/base.py
scalecodec/constants.py
scalecodec/exceptions.py
scalecodec/types.py
scalecodec/updater.py
scalecodec/type_registry/__init__.py
scalecodec/type_registry/acala.json
scalecodec/type_registry/canvas.json
scalecodec/type_registry/contracts-on-rococo.json
scalecodec/type_registry/core.json
scalecodec/type_registry/crust.json
scalecodec/type_registry/karura.json
scalecodec/type_registry/kusama.json
scalecodec/type_registry/legacy.json
scalecodec/type_registry/moonbase-alpha.json
scalecodec/type_registry/moonbeam.json
scalecodec/type_registry/moonriver.json
scalecodec/type_registry/polkadot.json
scalecodec/type_registry/polymesh-mainnet.json
scalecodec/type_registry/polymesh-testnet.json
scalecodec/type_registry/rococo.json
scalecodec/type_registry/statemine.json
scalecodec/type_registry/statemint.json
scalecodec/type_registry/substrate-node-template.json
scalecodec/type_registry/test.json
scalecodec/type_registry/westend.json
scalecodec/utils/__init__.py
scalecodec/utils/math.py
scalecodec/utils/ss58.py
scalecodec-1.2.12.dist-info/LICENSE
scalecodec-1.2.12.dist-info/METADATA
scalecodec-1.2.12.dist-info/WHEEL
scalecodec-1.2.12.dist-info/top_level.txt
scalecodec-1.2.12.dist-info/RECORD
