Metadata-Version: 2.1
Name: scalecodec
Version: 1.2.12
Summary: Python SCALE Codec Library
Home-page: https://github.com/polkascan/py-scale-codec
Author: Stichting Polkascan (Polkascan Foundation)
Author-email: info@polkascan.org
Keywords: scale codec polkascan polkadot substrate blockchain kusama
Classifier: Development Status :: 5 - Production/Stable
Classifier: Intended Audience :: Developers
Classifier: License :: OSI Approved :: Apache Software License
Classifier: Programming Language :: Python :: 3
Classifier: Programming Language :: Python :: 3.6
Classifier: Programming Language :: Python :: 3.7
Classifier: Programming Language :: Python :: 3.8
Classifier: Programming Language :: Python :: 3.9
Requires-Python: >=3.6, <4
Provides-Extra: test
License-File: LICENSE
